odoo10_addon_business_requirement_earned_value-10.0.1.0.0.99.dev2-py2.7-nspkg.pth
odoo/addons/business_requirement_earned_value/README.rst
odoo/addons/business_requirement_earned_value/__init__.py
odoo/addons/business_requirement_earned_value/__manifest__.py
odoo/addons/business_requirement_earned_value/demo/project_completion_report_demo.xml
odoo/addons/business_requirement_earned_value/i18n/business_requirement_earned_value.pot
odoo/addons/business_requirement_earned_value/models/__init__.py
odoo/addons/business_requirement_earned_value/models/br_and_project_inherit_function.py
odoo/addons/business_requirement_earned_value/report/__init__.py
odoo/addons/business_requirement_earned_value/report/project_completion_report.py
odoo/addons/business_requirement_earned_value/report/project_completion_report_view.xml
odoo/addons/business_requirement_earned_value/security/ir.model.access.csv
odoo/addons/business_requirement_earned_value/static/description/icon.png
odoo/addons/business_requirement_earned_value/static/img/correct_report.png
odoo/addons/business_requirement_earned_value/tests/__init__.py
odoo/addons/business_requirement_earned_value/tests/test_report_services.py
odoo/addons/business_requirement_earned_value/views/br_and_project_inherit_view.xml
odoo10_addon_business_requirement_earned_value-10.0.1.0.0.99.dev2.dist-info/METADATA
odoo10_addon_business_requirement_earned_value-10.0.1.0.0.99.dev2.dist-info/RECORD
odoo10_addon_business_requirement_earned_value-10.0.1.0.0.99.dev2.dist-info/WHEEL
odoo10_addon_business_requirement_earned_value-10.0.1.0.0.99.dev2.dist-info/namespace_packages.txt
odoo10_addon_business_requirement_earned_value-10.0.1.0.0.99.dev2.dist-info/top_level.txt
